surquest/GCP/logger/__init__.py
surquest/GCP/logger/json_encoder.py
surquest/GCP/logger/logger.py
surquest_gcp_logger-0.1.0.dist-info/METADATA
surquest_gcp_logger-0.1.0.dist-info/WHEEL
surquest_gcp_logger-0.1.0.dist-info/licenses/LICENSE
surquest_gcp_logger-0.1.0.dist-info/RECORD
