Metadata-Version: 2.1
Name: surquest-GCP-logger
Version: 0.1.0
Summary: Wrapper around Google Cloud Platform (GCP) logging library to simplify creation of traced logs.
Project-URL: Homepage, https://github.com/surquest/python-gcp-logger
Project-URL: Bug Tracker, https://github.com/surquest/python-gcp-logger/issues
Author-email: Michal Švarc <michal.svarc@surquest.com>
License-File: LICENSE
Requires-Dist: surquest-gcp-tracer~=0.1.0
Provides-Extra: test
Requires-Dist: pytest-cov>=4.0.0; extra == 'test'
Requires-Dist: pytest>=7.2.1; extra == 'test'
Requires-Dist: starlette>=0.24.0; extra == 'test'
